oiffmpeg/__init__.py
oiffmpeg/core.py
oiffmpeg/utils.py
oiffmpeg-0.2.0.dist-info/licenses/LICENSE
oiffmpeg-0.2.0.dist-info/METADATA
oiffmpeg-0.2.0.dist-info/WHEEL
oiffmpeg-0.2.0.dist-info/top_level.txt
oiffmpeg-0.2.0.dist-info/RECORD
