Metadata-Version: 2.4
Name: oiffmpeg
Version: 0.2.0
Summary: A simple Python wrapper for common FFmpeg CLI operations.
Author-email: Manus Team <contact@example.com>
License: MIT License
Project-URL: Homepage, https://github.com/example/oiffmpeg
Project-URL: Bug Tracker, https://github.com/example/oiffmpeg/issues
Keywords: ffmpeg,ffprobe,wrapper,video,audio,conversion,multimedia
Classifier: Programming Language :: Python :: 3
Classifier: License :: OSI Approved :: MIT License
Classifier: Operating System :: OS Independent
Classifier: Topic :: Multimedia :: Video :: Conversion
Classifier: Topic :: Multimedia :: Sound/Audio :: Conversion
Classifier: Intended Audience :: Developers
Classifier: Development Status :: 3 - Alpha
Requires-Python: >=3.7
License-File: LICENSE
Provides-Extra: dev
Requires-Dist: pytest; extra == "dev"
Requires-Dist: build; extra == "dev"
Requires-Dist: twine; extra == "dev"
Dynamic: license-file
